hydra_plugins/__init__.py
hydra_plugins/range_sweeper_badr/__init__.py
hydra_plugins/range_sweeper_badr/range_sweeper_badr.py
hydra_plugins/range_sweeper_badr/conf/__init__.py
hydra_plugins/range_sweeper_badr/conf/hydra/sweeper/range.yaml
hydra_range_sweeper_badr-0.1.3.dist-info/DESCRIPTION.rst
hydra_range_sweeper_badr-0.1.3.dist-info/METADATA
hydra_range_sweeper_badr-0.1.3.dist-info/RECORD
hydra_range_sweeper_badr-0.1.3.dist-info/WHEEL
hydra_range_sweeper_badr-0.1.3.dist-info/metadata.json
hydra_range_sweeper_badr-0.1.3.dist-info/top_level.txt
