Metadata-Version: 2.0
Name: hydra-range-sweeper-badr
Version: 0.1.3
Summary: Custom Hydra Range Sweeper plugin
Home-page: https://github.com/BadrYoubiIdrissi/hydra-plugins
Author: Badr Youbi Idrissi
Author-email: badryoubiidrissi@gmail.com
License: UNKNOWN
Platform: UNKNOWN
Classifier: License :: OSI Approved :: MIT License
Classifier: Programming Language :: Python :: 2.7
Classifier: Programming Language :: Python :: 3.6
Classifier: Programming Language :: Python :: 3.7
Classifier: Operating System :: OS Independent
Requires-Dist: hydra-core
